braket/ocean_plugin/__init__.py
braket/ocean_plugin/_version.py
braket/ocean_plugin/braket_dwave_sampler.py
braket/ocean_plugin/braket_sampler.py
braket/ocean_plugin/braket_solver_metadata.py
braket/ocean_plugin/exceptions.py
amazon_braket_ocean_plugin-1.0.11.dist-info/LICENSE
amazon_braket_ocean_plugin-1.0.11.dist-info/METADATA
amazon_braket_ocean_plugin-1.0.11.dist-info/NOTICE
amazon_braket_ocean_plugin-1.0.11.dist-info/WHEEL
amazon_braket_ocean_plugin-1.0.11.dist-info/top_level.txt
amazon_braket_ocean_plugin-1.0.11.dist-info/RECORD
