Metadata-Version: 2.1
Name: amazon-braket-ocean-plugin
Version: 1.0.11
Summary: An open source framework for interacting with D-Wave's Ocean library through Amazon Braket
Home-page: https://github.com/aws/amazon-braket-ocean-plugin-python
Author: Amazon Web Services
License: Apache License 2.0
Keywords: Amazon AWS Quantum
Platform: UNKNOWN
Classifier: Development Status :: 5 - Production/Stable
Classifier: Intended Audience :: Developers
Classifier: Natural Language :: English
Classifier: License :: OSI Approved :: Apache Software License
Classifier: Programming Language :: Python
Classifier: Programming Language :: Python :: 3.7
Classifier: Programming Language :: Python :: 3.8
Classifier: Programming Language :: Python :: 3.9
Requires-Python: >= 3.7
License-File: LICENSE
License-File: NOTICE
Requires-Dist: amazon-braket-sdk (>=1.25.0)
Requires-Dist: boto3 (>=1.18.13)
Requires-Dist: boltons (>=20.0.0)
Requires-Dist: colorama (>=0.4.3)
Requires-Dist: dimod (>=0.8.13)
Requires-Dist: dwave-cloud-client (>=0.9.4)
Requires-Dist: jsonref
Requires-Dist: wheel (>=0.36.2)
Provides-Extra: test
Requires-Dist: black ; extra == 'test'
Requires-Dist: flake8 ; extra == 'test'
Requires-Dist: isort ; extra == 'test'
Requires-Dist: pre-commit (>=2.13.0) ; extra == 'test'
Requires-Dist: pylint ; extra == 'test'
Requires-Dist: pytest (>=6.2.x) ; extra == 'test'
Requires-Dist: pytest-cov ; extra == 'test'
Requires-Dist: pytest-rerunfailures ; extra == 'test'
Requires-Dist: pytest-xdist ; extra == 'test'
Requires-Dist: sphinx (>=4.0.0) ; extra == 'test'
Requires-Dist: sphinx-rtd-theme ; extra == 'test'
Requires-Dist: sphinxcontrib-apidoc ; extra == 'test'
Requires-Dist: tox (>=3.23.0) ; extra == 'test'
Requires-Dist: dwave-ocean-sdk (>=3.4.0) ; extra == 'test'
